automata/__init__.py
automata/dfa.py
automata/turing_machine.py
automata_practical_mohamedaz-0.1.dist-info/METADATA
automata_practical_mohamedaz-0.1.dist-info/WHEEL
automata_practical_mohamedaz-0.1.dist-info/top_level.txt
automata_practical_mohamedaz-0.1.dist-info/RECORD
