Metadata-Version: 2.1
Name: automata-practical-mohamedaz
Version: 0.1
Summary: Automata Practical Exam - DFA and Turing Machine
Author: Mohamed Abd El-Azeem
Classifier: Programming Language :: Python :: 3
Classifier: License :: OSI Approved :: MIT License
Classifier: Operating System :: OS Independent
